setup.cfg
setup.py
identity_toolkit_python_client.egg-info/PKG-INFO
identity_toolkit_python_client.egg-info/SOURCES.txt
identity_toolkit_python_client.egg-info/dependency_links.txt
identity_toolkit_python_client.egg-info/pbr.json
identity_toolkit_python_client.egg-info/requires.txt
identity_toolkit_python_client.egg-info/top_level.txt
identitytoolkit/__init__.py
identitytoolkit/errors.py
identitytoolkit/gitkitclient.py
identitytoolkit/rpchelper.py