Metadata-Version: 1.1
Name: identity-toolkit-python-client
Version: 0.1.8
Summary: Google Identity Toolkit python client library
Home-page: https://github.com/google/identity-toolkit-python-client
Author: Jin Liu
Author-email: UNKNOWN
License: Apache 2.0
Download-URL: https://github.com/google/identity-toolkit-python-client/archive/master.zip
Keywords: identity,google,login,toolkit
Platform: UNKNOWN
Classifier: Development Status :: 5 - Production/Stable
Classifier: Intended Audience :: Developers
Classifier: License :: OSI Approved :: Apache Software License
Classifier: Operating System :: OS Independent
Classifier: Programming Language :: Python :: 2.7
Classifier: Programming Language :: Python :: 3.3
Classifier: Programming Language :: Python :: 3.4
Classifier: Topic :: Internet :: WWW/HTTP
